weather/__init__.py
weather/cli.py
weather/user_settings.py
weather/commands/__init__.py
weather/commands/base.py
weather/commands/today.py
weather/commands/week.py
openweathermap_cli-1.2.0.dist-info/METADATA
openweathermap_cli-1.2.0.dist-info/WHEEL
openweathermap_cli-1.2.0.dist-info/entry_points.txt
openweathermap_cli-1.2.0.dist-info/top_level.txt
openweathermap_cli-1.2.0.dist-info/RECORD
